lookatme/contrib/image_ueberzug.py
lookatme.contrib.image_ueberzug-1.1.0.dist-info/LICENSE
lookatme.contrib.image_ueberzug-1.1.0.dist-info/METADATA
lookatme.contrib.image_ueberzug-1.1.0.dist-info/WHEEL
lookatme.contrib.image_ueberzug-1.1.0.dist-info/top_level.txt
lookatme.contrib.image_ueberzug-1.1.0.dist-info/RECORD
