Metadata-Version: 2.1
Name: lookatme.contrib.image-ueberzug
Version: 1.1.0
Summary: An image renderer that uses ueberzug
Home-page: https://github.com/d0c-s4vage/lookatme.contrib.image_ueberzug
Author: James Johnson
Author-email: d0c.s4vage@gmail.com
License: UNKNOWN
Platform: UNKNOWN
Classifier: Environment :: Console
Classifier: Environment :: Plugins
Classifier: Intended Audience :: Developers
Classifier: License :: OSI Approved :: MIT License
Classifier: Operating System :: OS Independent
Classifier: Programming Language :: Python :: 3
Classifier: Programming Language :: Python :: 3 :: Only
Classifier: Topic :: Multimedia :: Graphics :: Presentation
Classifier: Topic :: Software Development :: Documentation
Requires-Python: >=3.6
Requires-Dist: lookatme (<3.0.0,>=2.0.0)
Requires-Dist: urwid-ueberzogen (<1.0.0,>=0.0.4)
Requires-Dist: ueberzug (<19,>=18)
